artix/__init__.py
artix/cli.py
artix/config.py
artix-0.0.1.dist-info/LICENSE
artix-0.0.1.dist-info/METADATA
artix-0.0.1.dist-info/WHEEL
artix-0.0.1.dist-info/entry_points.txt
artix-0.0.1.dist-info/RECORD
