Metadata-Version: 2.1
Name: artix
Version: 0.0.1
Summary: A generic artifact management utility.
License: MIT
Author: celestialorb
Author-email: chris.m.busby@gmail.com
Requires-Python: >=3.12,<4.0
Classifier: License :: OSI Approved :: MIT License
Classifier: Programming Language :: Python :: 3
Classifier: Programming Language :: Python :: 3.12
Requires-Dist: click (>=8.1.7,<9.0.0)
Requires-Dist: importlib-metadata (>=8.2.0,<9.0.0)
Requires-Dist: loguru (>=0.7.2,<0.8.0)
Requires-Dist: packaging (>=24.1,<25.0)
Requires-Dist: requests (>=2.32.3,<3.0.0)
Requires-Dist: rich-click (>=1.8.3,<2.0.0)
Requires-Dist: tomli (>=2.0.1,<3.0.0)
